telex_python_apm/__init__.py
telex_python_apm/fastapi/__init__.py
telex_python_apm/fastapi/middleware.py
telex_python_apm/fastapi/tests/__init__.py
telex_python_apm/fastapi/tests/test_middleware.py
telex_python_apm-0.1.5.dist-info/METADATA
telex_python_apm-0.1.5.dist-info/WHEEL
telex_python_apm-0.1.5.dist-info/top_level.txt
telex_python_apm-0.1.5.dist-info/RECORD
