Metadata-Version: 2.1
Name: telex_python_apm
Version: 0.1.5
Summary: Telex APM middleware for FastAPI.
Author: Cyberguru1
Author-email: hamzacypher34@gmail.com
Classifier: Programming Language :: Python :: 3
Classifier: License :: OSI Approved :: MIT License
Classifier: Operating System :: OS Independent
Requires-Dist: fastapi
Requires-Dist: httpx
Requires-Dist: starlette
